dalia_dif/.DS_Store
dalia_dif/__init__.py
dalia_dif/__main__.py
dalia_dif/cli.py
dalia_dif/dif13/__init__.py
dalia_dif/dif13/community/__init__.py
dalia_dif/dif13/community/dalia_communities.csv
dalia_dif/dif13/constants.py
dalia_dif/dif13/export/__init__.py
dalia_dif/dif13/export/charts.py
dalia_dif/dif13/export/fti.py
dalia_dif/dif13/legacy/__init__.py
dalia_dif/dif13/legacy/authors.py
dalia_dif/dif13/legacy/components.py
dalia_dif/dif13/legacy/learning_resource.py
dalia_dif/dif13/model.py
dalia_dif/dif13/picklists.py
dalia_dif/dif13/predicates.py
dalia_dif/dif13/rdf.py
dalia_dif/dif13/reader.py
dalia_dif/dif13/utils.py
dalia_dif/namespace/__init__.py
dalia_dif/namespace/bibframe_lite_relation.py
dalia_dif/namespace/bibo.py
dalia_dif/namespace/citedcat.py
dalia_dif/namespace/educor.py
dalia_dif/namespace/fabio.py
dalia_dif/namespace/hcrt.py
dalia_dif/namespace/metadata4ing.py
dalia_dif/namespace/modalia.py
dalia_dif/namespace/rec.py
dalia_dif/py.typed
dalia_dif/utils.py
dalia_dif/version.py
dalia_dif-0.0.17.dist-info/licenses/LICENSE
dalia_dif-0.0.17.dist-info/WHEEL
dalia_dif-0.0.17.dist-info/entry_points.txt
dalia_dif-0.0.17.dist-info/METADATA
dalia_dif-0.0.17.dist-info/RECORD
