Metadata-Version: 2.4
Name: dalia_dif
Version: 0.0.17
Summary: Tools for DALIA's data model for open educational resources
Keywords: snekpack,cookiecutter,open educational resources,educational resources,training
Author: Charles Tapley Hoyt
Author-email: Charles Tapley Hoyt <cthoyt@gmail.com>
License-File: LICENSE
Classifier: Development Status :: 1 - Planning
Classifier: Environment :: Console
Classifier: Intended Audience :: Developers
Classifier: License :: OSI Approved :: MIT License
Classifier: Operating System :: OS Independent
Classifier: Framework :: Pytest
Classifier: Framework :: tox
Classifier: Framework :: Sphinx
Classifier: Natural Language :: English
Classifier: Programming Language :: Python
Classifier: Programming Language :: Python :: 3.10
Classifier: Programming Language :: Python :: 3.11
Classifier: Programming Language :: Python :: 3.12
Classifier: Programming Language :: Python :: 3.13
Classifier: Programming Language :: Python :: 3 :: Only
Classifier: Typing :: Typed
Requires-Dist: click
Requires-Dist: pydantic
Requires-Dist: pydantic-extra-types[pycountry]
Requires-Dist: pydantic-metamodel
Requires-Dist: pystow
Requires-Dist: rdflib
Requires-Dist: tqdm
Requires-Dist: curies
Requires-Dist: base32-crockford
Requires-Dist: matplotlib ; extra == 'export'
Requires-Dist: seaborn ; extra == 'export'
Requires-Dist: pandas ; extra == 'export'
Requires-Dist: pandas ; extra == 'fti'
Maintainer: Charles Tapley Hoyt
Maintainer-email: Charles Tapley Hoyt <cthoyt@gmail.com>
Requires-Python: >=3.10
Project-URL: Bug Tracker, https://github.com/data-literacy-alliance/dalia-dif/issues
Project-URL: Documentation, https://dalia-dif.readthedocs.io
Project-URL: Homepage, https://github.com/data-literacy-alliance/dalia-dif
Project-URL: Repository, https://github.com/data-literacy-alliance/dalia-dif.git
Provides-Extra: export
Provides-Extra: fti
